mangagraph/__init__.py
mangagraph/__main__.py
mangagraph/cli.py
mangagraph/constants.py
mangagraph/exceptions.py
mangagraph/models.py
mangagraph/parser.py
mangagraph/schemas.py
mangagraph/utils.py
mangagraph-0.1.0.dist-info/METADATA
mangagraph-0.1.0.dist-info/WHEEL
mangagraph-0.1.0.dist-info/top_level.txt
mangagraph-0.1.0.dist-info/RECORD
