Metadata-Version: 2.4
Name: mangagraph
Version: 0.1.0
Summary: Async manga parser-converter from mangalib to telegraph pages
Home-page: https://github.com/damirTAG/mangagraph
Author: damirTAG
Author-email: damirtagilbayev17@gmail.com
License: MIT
Project-URL: Bug Reports, https://github.com/damirTAG/mangagraph/issues
Project-URL: Source, https://github.com/damirTAG/mangagraph
Project-URL: Telegram, https://t.me/damirtag
Keywords: mangalib,mangalib-parser,manga,telegraph,async,parser,converter,web-scraping
Classifier: Development Status :: 3 - Alpha
Classifier: Intended Audience :: Developers
Classifier: Topic :: Software Development :: Libraries :: Python Modules
Classifier: Topic :: Internet :: WWW/HTTP
Classifier: License :: OSI Approved :: MIT License
Classifier: Programming Language :: Python :: 3
Classifier: Programming Language :: Python :: 3.8
Classifier: Programming Language :: Python :: 3.9
Classifier: Programming Language :: Python :: 3.10
Classifier: Programming Language :: Python :: 3.11
Classifier: Programming Language :: Python :: 3.12
Classifier: Programming Language :: Python :: 3 :: Only
Classifier: Operating System :: OS Independent
Classifier: Framework :: AsyncIO
Classifier: Typing :: Typed
Requires-Python: >=3.8
Requires-Dist: aiohttp>=3.8.0
Requires-Dist: sqlalchemy>=1.4.0
Requires-Dist: telegraph>=2.2.0
Provides-Extra: dev
Requires-Dist: pytest>=7.0.0; extra == "dev"
Requires-Dist: pytest-asyncio>=0.21.0; extra == "dev"
Requires-Dist: black>=23.0.0; extra == "dev"
Requires-Dist: flake8>=6.0.0; extra == "dev"
Dynamic: author
Dynamic: author-email
Dynamic: classifier
Dynamic: description
Dynamic: description-content-type
Dynamic: home-page
Dynamic: keywords
Dynamic: license
Dynamic: project-url
Dynamic: provides-extra
Dynamic: requires-dist
Dynamic: requires-python
Dynamic: summary
